SerasaLib-0.0.3.dist-info/DESCRIPTION.rst
SerasaLib-0.0.3.dist-info/METADATA
SerasaLib-0.0.3.dist-info/RECORD
SerasaLib-0.0.3.dist-info/WHEEL
SerasaLib-0.0.3.dist-info/metadata.json
SerasaLib-0.0.3.dist-info/top_level.txt
serasaapi/__init__.py
