Metadata-Version: 2.0
Name: SerasaLib
Version: 0.0.3
Summary: Transmissao de arquivos (Sandbox)
Home-page: UNKNOWN
Author: FastDeploy
Author-email: fastdeploy@dextra-sw.com
License: UNKNOWN
Platform: UNKNOWN
Classifier: Programming Language :: Python :: 3
Classifier: License :: OSI Approved :: MIT License
Classifier: Operating System :: OS Independent
